attrdict_rog/__init__.py
attrdict_rog/default.py
attrdict_rog/dictionary.py
attrdict_rog/mapping.py
attrdict_rog/merge.py
attrdict_rog/mixins.py
attrdict_rog-1.0.0.dist-info/LICENSE.txt
attrdict_rog-1.0.0.dist-info/METADATA
attrdict_rog-1.0.0.dist-info/WHEEL
attrdict_rog-1.0.0.dist-info/top_level.txt
attrdict_rog-1.0.0.dist-info/zip-safe
attrdict_rog-1.0.0.dist-info/RECORD
