Metadata-Version: 2.1
Name: attrdict_rog
Version: 1.0.0
Summary: A dict with attribute-style access
Home-page: https://github.com/root-gift/attrdict-rog.git
Author: Michael Roger ZONGO
Author-email: michaelrogerzongo@gmail.com
License: MIT License
Classifier: Development Status :: 7 - Inactive
Classifier: Intended Audience :: Developers
Classifier: License :: OSI Approved :: MIT License
Classifier: Programming Language :: Python :: 2
Classifier: Programming Language :: Python :: 2.7
Classifier: Programming Language :: Python :: 3
Classifier: Programming Language :: Python :: Implementation :: CPython
Classifier: Programming Language :: Python :: Implementation :: PyPy
License-File: LICENSE.txt
Requires-Dist: six
